{
    "geometries": [{
        "materials": [{
            "specularCoef": 50,
            "blending": "NormalBlending",
            "transparent": false,
            "colorEmissive": [0,0,0],
            "colorAmbient": [1,1,1],
            "shading": "phong",
            "mapSpecularWrap": ["RepeatWrapping","RepeatWrapping"],
            "depthWrite": true,
            "depthTest": true,
            "mapSpecularAnisotropy": 1,
            "mapDiffuseRepeat": [1,1],
            "opacity": 1,
            "mapDiffuse": "WoodDark_COLOR.png",
            "DbgColor": 15658734,
            "mapSpecularRepeat": [1,1],
            "mapDiffuseWrap": ["RepeatWrapping","RepeatWrapping"],
            "doubleSided": true,
            "mapDiffuseAnisotropy": 1,
            "colorSpecular": [0.004706,0.004706,0.004314],
            "DbgIndex": 0,
            "colorDiffuse": [1,1,1],
            "DbgName": "Wood_Dark_Polished",
            "mapSpecular": "WoodDark_SPEC.png",
            "visible": true,
            "wireframe": false
        }],
        "uuid": "778708C3-2A4C-30ED-AC23-F99783DFA888",
        "data": {
            "metadata": {
                "faces": 6,
                "generator": "io_three",
                "materials": 1,
                "bones": 0,
                "morphTargets": 0,
                "version": 3,
                "vertices": 8,
                "normals": 8,
                "uvs": 1
            },
            "skinIndices": [],
            "influencesPerVertex": 2,
            "morphTargets": [],
            "animations": [],
            "normals": [0.577349,-0.577349,0.577349,0.577349,-0.577349,-0.577349,0.577349,0.577349,-0.577349,0.577349,0.577349,0.577349,-0.577349,0.577349,0.577349,-0.577349,0.577349,-0.577349,-0.577349,-0.577349,-0.577349,-0.577349,-0.577349,0.577349],
            "skinWeights": [],
            "faces": [43,0,2,3,1,0,0,1,2,3,0,1,2,3,43,4,6,7,5,0,0,1,2,3,4,5,6,7,43,0,1,4,5,0,2,3,0,1,0,3,4,7,43,7,6,3,2,0,0,1,2,3,6,5,2,1,43,2,0,5,7,0,2,3,0,1,1,0,7,6,43,1,3,6,4,0,0,1,2,3,3,2,5,4],
            "bones": [],
            "name": "Box7Geometry",
            "vertices": [0.5,-0.5,0.5,0.5,0.5,0.5,0.5,-0.5,-0.5,0.5,0.5,-0.5,-0.5,0.5,0.5,-0.5,-0.5,0.5,-0.5,0.5,-0.5,-0.5,-0.5,-0.5],
            "uvs": [[0,1,0,0,1,0,1,1]]
        },
        "type": "Geometry"
    },{
        "materials": [{
            "specularCoef": 50,
            "blending": "NormalBlending",
            "transparent": false,
            "colorEmissive": [0,0,0],
            "colorAmbient": [1,1,1],
            "shading": "phong",
            "mapSpecularWrap": ["RepeatWrapping","RepeatWrapping"],
            "depthWrite": true,
            "depthTest": true,
            "mapSpecularAnisotropy": 1,
            "mapDiffuseRepeat": [1,1],
            "opacity": 1,
            "mapDiffuse": "WoodDark_COLOR.png",
            "DbgColor": 15658734,
            "mapSpecularRepeat": [1,1],
            "mapDiffuseWrap": ["RepeatWrapping","RepeatWrapping"],
            "doubleSided": true,
            "mapDiffuseAnisotropy": 1,
            "colorSpecular": [0.004706,0.004706,0.004314],
            "DbgIndex": 0,
            "colorDiffuse": [1,1,1],
            "DbgName": "Wood_Dark_Polished",
            "mapSpecular": "WoodDark_SPEC.png",
            "visible": true,
            "wireframe": false
        }],
        "uuid": "21064AED-2F9E-349A-8048-33069A9BEACE",
        "data": {
            "metadata": {
                "faces": 6,
                "generator": "io_three",
                "materials": 1,
                "bones": 0,
                "morphTargets": 0,
                "version": 3,
                "vertices": 8,
                "normals": 8,
                "uvs": 1
            },
            "skinIndices": [],
            "influencesPerVertex": 2,
            "morphTargets": [],
            "animations": [],
            "normals": [0.577349,-0.577349,0.577349,0.577349,-0.577349,-0.577349,0.577349,0.577349,-0.577349,0.577349,0.577349,0.577349,-0.577349,0.577349,0.577349,-0.577349,0.577349,-0.577349,-0.577349,-0.577349,-0.577349,-0.577349,-0.577349,0.577349],
            "skinWeights": [],
            "faces": [43,0,2,3,1,0,0,1,2,3,0,1,2,3,43,4,6,7,5,0,0,1,2,3,4,5,6,7,43,0,1,4,5,0,2,3,0,1,0,3,4,7,43,7,6,3,2,0,0,1,2,3,6,5,2,1,43,2,0,5,7,0,2,3,0,1,1,0,7,6,43,1,3,6,4,0,0,1,2,3,3,2,5,4],
            "bones": [],
            "name": "Box4Geometry",
            "vertices": [0.5,-0.5,0.5,0.5,0.5,0.5,0.5,-0.5,-0.5,0.5,0.5,-0.5,-0.5,0.5,0.5,-0.5,-0.5,0.5,-0.5,0.5,-0.5,-0.5,-0.5,-0.5],
            "uvs": [[0,1,0,0,1,0,1,1]]
        },
        "type": "Geometry"
    },{
        "materials": [{
            "specularCoef": 50,
            "blending": "NormalBlending",
            "transparent": false,
            "colorEmissive": [0,0,0],
            "colorAmbient": [1,1,1],
            "shading": "phong",
            "mapSpecularWrap": ["RepeatWrapping","RepeatWrapping"],
            "depthWrite": true,
            "depthTest": true,
            "mapSpecularAnisotropy": 1,
            "mapDiffuseRepeat": [1,1],
            "opacity": 1,
            "mapDiffuse": "WoodDark_COLOR.png",
            "DbgColor": 15658734,
            "mapSpecularRepeat": [1,1],
            "mapDiffuseWrap": ["RepeatWrapping","RepeatWrapping"],
            "doubleSided": true,
            "mapDiffuseAnisotropy": 1,
            "colorSpecular": [0.004706,0.004706,0.004314],
            "DbgIndex": 0,
            "colorDiffuse": [1,1,1],
            "DbgName": "Wood_Dark_Polished",
            "mapSpecular": "WoodDark_SPEC.png",
            "visible": true,
            "wireframe": false
        }],
        "uuid": "64183BD0-6EAE-3D88-8ABC-1117C3AD9D35",
        "data": {
            "metadata": {
                "faces": 6,
                "generator": "io_three",
                "materials": 1,
                "bones": 0,
                "morphTargets": 0,
                "version": 3,
                "vertices": 8,
                "normals": 8,
                "uvs": 1
            },
            "skinIndices": [],
            "influencesPerVertex": 2,
            "morphTargets": [],
            "animations": [],
            "normals": [0.577349,-0.577349,0.577349,0.577349,-0.577349,-0.577349,0.577349,0.577349,-0.577349,0.577349,0.577349,0.577349,-0.577349,0.577349,0.577349,-0.577349,0.577349,-0.577349,-0.577349,-0.577349,-0.577349,-0.577349,-0.577349,0.577349],
            "skinWeights": [],
            "faces": [43,0,2,3,1,0,0,1,2,3,0,1,2,3,43,4,6,7,5,0,0,1,2,3,4,5,6,7,43,0,1,4,5,0,2,3,0,1,0,3,4,7,43,7,6,3,2,0,0,1,2,3,6,5,2,1,43,2,0,5,7,0,2,3,0,1,1,0,7,6,43,1,3,6,4,0,0,1,2,3,3,2,5,4],
            "bones": [],
            "name": "Box5Geometry",
            "vertices": [0.5,-0.5,0.5,0.5,0.5,0.5,0.5,-0.5,-0.5,0.5,0.5,-0.5,-0.5,0.5,0.5,-0.5,-0.5,0.5,-0.5,0.5,-0.5,-0.5,-0.5,-0.5],
            "uvs": [[0,1,0,0,1,0,1,1]]
        },
        "type": "Geometry"
    },{
        "materials": [{
            "specularCoef": 50,
            "blending": "NormalBlending",
            "transparent": false,
            "colorEmissive": [0,0,0],
            "colorAmbient": [1,1,1],
            "shading": "phong",
            "mapSpecularWrap": ["RepeatWrapping","RepeatWrapping"],
            "depthWrite": true,
            "depthTest": true,
            "mapSpecularAnisotropy": 1,
            "mapDiffuseRepeat": [1,1],
            "opacity": 1,
            "mapDiffuse": "WoodDark_COLOR.png",
            "DbgColor": 15658734,
            "mapSpecularRepeat": [1,1],
            "mapDiffuseWrap": ["RepeatWrapping","RepeatWrapping"],
            "doubleSided": true,
            "mapDiffuseAnisotropy": 1,
            "colorSpecular": [0.004706,0.004706,0.004314],
            "DbgIndex": 0,
            "colorDiffuse": [1,1,1],
            "DbgName": "Wood_Dark_Polished",
            "mapSpecular": "WoodDark_SPEC.png",
            "visible": true,
            "wireframe": false
        }],
        "uuid": "15641190-4052-3871-BF5E-F046F6B1B496",
        "data": {
            "metadata": {
                "faces": 6,
                "generator": "io_three",
                "materials": 1,
                "bones": 0,
                "morphTargets": 0,
                "version": 3,
                "vertices": 8,
                "normals": 8,
                "uvs": 1
            },
            "skinIndices": [],
            "influencesPerVertex": 2,
            "morphTargets": [],
            "animations": [],
            "normals": [0.577349,-0.577349,0.577349,0.577349,-0.577349,-0.577349,0.577349,0.577349,-0.577349,0.577349,0.577349,0.577349,-0.577349,0.577349,0.577349,-0.577349,0.577349,-0.577349,-0.577349,-0.577349,-0.577349,-0.577349,-0.577349,0.577349],
            "skinWeights": [],
            "faces": [43,0,2,3,1,0,0,1,2,3,0,1,2,3,43,4,6,7,5,0,0,1,2,3,4,5,6,7,43,0,1,4,5,0,2,3,0,1,0,3,4,7,43,7,6,3,2,0,0,1,2,3,6,5,2,1,43,2,0,5,7,0,2,3,0,1,1,0,7,6,43,1,3,6,4,0,0,1,2,3,3,2,5,4],
            "bones": [],
            "name": "BoxGeometry",
            "vertices": [11.5,-2.75,0.125,11.5,2.75,0.125,11.5,-2.75,-0.125,11.5,2.75,-0.125,-11.5,2.75,0.125,-11.5,-2.75,0.125,-11.5,2.75,-0.125,-11.5,-2.75,-0.125],
            "uvs": [[0,1,0,0,1,0,1,1]]
        },
        "type": "Geometry"
    },{
        "materials": [{
            "specularCoef": 50,
            "blending": "NormalBlending",
            "transparent": false,
            "DbgIndex": 0,
            "colorEmissive": [0,0,0],
            "colorAmbient": [1,0,0],
            "shading": "phong",
            "depthWrite": true,
            "depthTest": true,
            "colorDiffuse": [1,0,0],
            "colorSpecular": [0.012,0.012,0.012],
            "DbgName": "Physical2",
            "opacity": 1,
            "doubleSided": true,
            "DbgColor": 15658734,
            "visible": true,
            "wireframe": false
        }],
        "uuid": "98CE0ABF-982E-3010-BF1D-01919C9CB4EF",
        "data": {
            "metadata": {
                "faces": 6,
                "generator": "io_three",
                "materials": 1,
                "bones": 0,
                "morphTargets": 0,
                "version": 3,
                "vertices": 8,
                "normals": 8,
                "uvs": 1
            },
            "skinIndices": [],
            "influencesPerVertex": 2,
            "morphTargets": [],
            "animations": [],
            "normals": [0.577349,-0.577349,0.577349,0.577349,-0.577349,-0.577349,0.577349,0.577349,-0.577349,0.577349,0.577349,0.577349,-0.577349,0.577349,0.577349,-0.577349,0.577349,-0.577349,-0.577349,-0.577349,-0.577349,-0.577349,-0.577349,0.577349],
            "skinWeights": [],
            "faces": [43,0,2,3,1,0,0,1,2,3,0,1,2,3,43,4,6,7,5,0,0,1,2,3,4,5,6,7,43,0,1,4,5,0,2,3,0,1,0,3,4,7,43,7,6,3,2,0,0,1,2,3,6,5,2,1,43,2,0,5,7,0,2,3,0,1,1,0,7,6,43,1,3,6,4,0,0,1,2,3,3,2,5,4],
            "bones": [],
            "name": "Box9Geometry",
            "vertices": [0.5,-0.5,0.5,0.5,0.5,0.5,0.5,-0.5,-0.5,0.5,0.5,-0.5,-0.5,0.5,0.5,-0.5,-0.5,0.5,-0.5,0.5,-0.5,-0.5,-0.5,-0.5],
            "uvs": [[0,1,0,0,1,0,1,1]]
        },
        "type": "Geometry"
    },{
        "materials": [{
            "specularCoef": 50,
            "blending": "NormalBlending",
            "transparent": false,
            "colorEmissive": [0,0,0],
            "colorAmbient": [1,1,1],
            "shading": "phong",
            "mapSpecularWrap": ["RepeatWrapping","RepeatWrapping"],
            "depthWrite": true,
            "depthTest": true,
            "mapSpecularAnisotropy": 1,
            "mapDiffuseRepeat": [1,1],
            "opacity": 1,
            "mapDiffuse": "WoodDark_COLOR.png",
            "DbgColor": 15658734,
            "mapSpecularRepeat": [1,1],
            "mapDiffuseWrap": ["RepeatWrapping","RepeatWrapping"],
            "doubleSided": true,
            "mapDiffuseAnisotropy": 1,
            "colorSpecular": [0.004706,0.004706,0.004314],
            "DbgIndex": 0,
            "colorDiffuse": [1,1,1],
            "DbgName": "Wood_Dark_Polished",
            "mapSpecular": "WoodDark_SPEC.png",
            "visible": true,
            "wireframe": false
        }],
        "uuid": "5B23DCE7-72A6-31B5-B561-B5098FF6433E",
        "data": {
            "metadata": {
                "faces": 6,
                "generator": "io_three",
                "materials": 1,
                "bones": 0,
                "morphTargets": 0,
                "version": 3,
                "vertices": 8,
                "normals": 8,
                "uvs": 1
            },
            "skinIndices": [],
            "influencesPerVertex": 2,
            "morphTargets": [],
            "animations": [],
            "normals": [0.577349,-0.577349,0.577349,0.577349,-0.577349,-0.577349,0.577349,0.577349,-0.577349,0.577349,0.577349,0.577349,-0.577349,0.577349,0.577349,-0.577349,0.577349,-0.577349,-0.577349,-0.577349,-0.577349,-0.577349,-0.577349,0.577349],
            "skinWeights": [],
            "faces": [43,0,2,3,1,0,0,1,2,3,0,1,2,3,43,4,6,7,5,0,0,1,2,3,4,5,6,7,43,0,1,4,5,0,2,3,0,1,0,3,4,7,43,7,6,3,2,0,0,1,2,3,6,5,2,1,43,2,0,5,7,0,2,3,0,1,1,0,7,6,43,1,3,6,4,0,0,1,2,3,3,2,5,4],
            "bones": [],
            "name": "Box10Geometry",
            "vertices": [6.5,-2.75,0.075,6.5,2.75,0.075,6.5,-2.75,-0.075,6.5,2.75,-0.075,-6.5,2.75,0.075,-6.5,-2.75,0.075,-6.5,2.75,-0.075,-6.5,-2.75,-0.075],
            "uvs": [[0,1,0,0,1,0,1,1]]
        },
        "type": "Geometry"
    },{
        "materials": [{
            "specularCoef": 50,
            "blending": "NormalBlending",
            "transparent": false,
            "colorEmissive": [0,0,0],
            "colorAmbient": [1,1,1],
            "shading": "phong",
            "mapSpecularWrap": ["RepeatWrapping","RepeatWrapping"],
            "depthWrite": true,
            "depthTest": true,
            "mapSpecularAnisotropy": 1,
            "mapDiffuseRepeat": [1,1],
            "opacity": 1,
            "mapDiffuse": "WoodDark_COLOR.png",
            "DbgColor": 15658734,
            "mapSpecularRepeat": [1,1],
            "mapDiffuseWrap": ["RepeatWrapping","RepeatWrapping"],
            "doubleSided": true,
            "mapDiffuseAnisotropy": 1,
            "colorSpecular": [0.004706,0.004706,0.004314],
            "DbgIndex": 0,
            "colorDiffuse": [1,1,1],
            "DbgName": "Wood_Dark_Polished",
            "mapSpecular": "WoodDark_SPEC.png",
            "visible": true,
            "wireframe": false
        }],
        "uuid": "5F05442A-9704-3BFB-BE1B-EE12E2150EE3",
        "data": {
            "metadata": {
                "faces": 6,
                "generator": "io_three",
                "materials": 1,
                "bones": 0,
                "morphTargets": 0,
                "version": 3,
                "vertices": 8,
                "normals": 8,
                "uvs": 1
            },
            "skinIndices": [],
            "influencesPerVertex": 2,
            "morphTargets": [],
            "animations": [],
            "normals": [0.577349,-0.577349,0.577349,0.577349,-0.577349,-0.577349,0.577349,0.577349,-0.577349,0.577349,0.577349,0.577349,-0.577349,0.577349,0.577349,-0.577349,0.577349,-0.577349,-0.577349,-0.577349,-0.577349,-0.577349,-0.577349,0.577349],
            "skinWeights": [],
            "faces": [43,0,2,3,1,0,0,1,2,3,0,1,2,3,43,4,6,7,5,0,0,1,2,3,4,5,6,7,43,0,1,4,5,0,2,3,0,1,0,3,4,7,43,7,6,3,2,0,0,1,2,3,6,5,2,1,43,2,0,5,7,0,2,3,0,1,1,0,7,6,43,1,3,6,4,0,0,1,2,3,3,2,5,4],
            "bones": [],
            "name": "Box6Geometry",
            "vertices": [0.5,-0.5,0.5,0.5,0.5,0.5,0.5,-0.5,-0.5,0.5,0.5,-0.5,-0.5,0.5,0.5,-0.5,-0.5,0.5,-0.5,0.5,-0.5,-0.5,-0.5,-0.5],
            "uvs": [[0,1,0,0,1,0,1,1]]
        },
        "type": "Geometry"
    },{
        "materials": [{
            "specularCoef": 50,
            "blending": "NormalBlending",
            "transparent": false,
            "DbgIndex": 0,
            "colorEmissive": [0,0,0],
            "colorAmbient": [1,0,0],
            "shading": "phong",
            "depthWrite": true,
            "depthTest": true,
            "colorDiffuse": [1,0,0],
            "colorSpecular": [0.012,0.012,0.012],
            "DbgName": "Physical1",
            "opacity": 1,
            "doubleSided": true,
            "DbgColor": 15658734,
            "visible": true,
            "wireframe": false
        }],
        "uuid": "A3266DF7-EF8B-3835-B919-F2D9B9D10D07",
        "data": {
            "metadata": {
                "faces": 6,
                "generator": "io_three",
                "materials": 1,
                "bones": 0,
                "morphTargets": 0,
                "version": 3,
                "vertices": 8,
                "normals": 8,
                "uvs": 1
            },
            "skinIndices": [],
            "influencesPerVertex": 2,
            "morphTargets": [],
            "animations": [],
            "normals": [0.577349,-0.577349,0.577349,0.577349,-0.577349,-0.577349,0.577349,0.577349,-0.577349,0.577349,0.577349,0.577349,-0.577349,0.577349,0.577349,-0.577349,0.577349,-0.577349,-0.577349,-0.577349,-0.577349,-0.577349,-0.577349,0.577349],
            "skinWeights": [],
            "faces": [43,0,2,3,1,0,0,1,2,3,0,1,2,3,43,4,6,7,5,0,0,1,2,3,4,5,6,7,43,0,1,4,5,0,2,3,0,1,0,3,4,7,43,7,6,3,2,0,0,1,2,3,6,5,2,1,43,2,0,5,7,0,2,3,0,1,1,0,7,6,43,1,3,6,4,0,0,1,2,3,3,2,5,4],
            "bones": [],
            "name": "Box2Geometry",
            "vertices": [11.5,-2.75,0.125,11.5,2.75,0.125,11.5,-2.75,-0.125,11.5,2.75,-0.125,-11.5,2.75,0.125,-11.5,-2.75,0.125,-11.5,2.75,-0.125,-11.5,-2.75,-0.125],
            "uvs": [[0,1,0,0,1,0,1,1]]
        },
        "type": "Geometry"
    },{
        "materials": [{
            "specularCoef": 50,
            "blending": "NormalBlending",
            "transparent": false,
            "colorEmissive": [0,0,0],
            "colorAmbient": [1,1,1],
            "shading": "phong",
            "mapSpecularWrap": ["RepeatWrapping","RepeatWrapping"],
            "depthWrite": true,
            "depthTest": true,
            "mapSpecularAnisotropy": 1,
            "mapDiffuseRepeat": [1,1],
            "opacity": 1,
            "mapDiffuse": "WoodDark_COLOR.png",
            "DbgColor": 15658734,
            "mapSpecularRepeat": [1,1],
            "mapDiffuseWrap": ["RepeatWrapping","RepeatWrapping"],
            "doubleSided": true,
            "mapDiffuseAnisotropy": 1,
            "colorSpecular": [0.004706,0.004706,0.004314],
            "DbgIndex": 0,
            "colorDiffuse": [1,1,1],
            "DbgName": "Wood_Dark_Polished",
            "mapSpecular": "WoodDark_SPEC.png",
            "visible": true,
            "wireframe": false
        }],
        "uuid": "DAF26EED-E8A1-3597-94D1-E65246622C91",
        "data": {
            "metadata": {
                "faces": 6,
                "generator": "io_three",
                "materials": 1,
                "bones": 0,
                "morphTargets": 0,
                "version": 3,
                "vertices": 8,
                "normals": 8,
                "uvs": 1
            },
            "skinIndices": [],
            "influencesPerVertex": 2,
            "morphTargets": [],
            "animations": [],
            "normals": [0.577349,-0.577349,0.577349,0.577349,-0.577349,-0.577349,0.577349,0.577349,-0.577349,0.577349,0.577349,0.577349,-0.577349,0.577349,0.577349,-0.577349,0.577349,-0.577349,-0.577349,-0.577349,-0.577349,-0.577349,-0.577349,0.577349],
            "skinWeights": [],
            "faces": [43,0,2,3,1,0,0,1,2,3,0,1,2,3,43,4,6,7,5,0,0,1,2,3,4,5,6,7,43,0,1,4,5,0,2,3,0,1,0,3,4,7,43,7,6,3,2,0,0,1,2,3,6,5,2,1,43,2,0,5,7,0,2,3,0,1,1,0,7,6,43,1,3,6,4,0,0,1,2,3,3,2,5,4],
            "bones": [],
            "name": "Box3Geometry",
            "vertices": [0.5,-0.5,0.5,0.5,0.5,0.5,0.5,-0.5,-0.5,0.5,0.5,-0.5,-0.5,0.5,0.5,-0.5,-0.5,0.5,-0.5,0.5,-0.5,-0.5,-0.5,-0.5],
            "uvs": [[0,1,0,0,1,0,1,1]]
        },
        "type": "Geometry"
    },{
        "materials": [],
        "uuid": "18A4CCFE-A980-31C8-A6B9-F2DC0A012554",
        "data": {
            "metadata": {
                "generator": "io_three",
                "materials": 0,
                "bones": 0,
                "morphTargets": 0,
                "version": 3,
                "vertices": 0,
                "normals": 0,
                "uvs": 0
            },
            "skinIndices": [],
            "influencesPerVertex": 2,
            "morphTargets": [],
            "animations": [],
            "normals": [],
            "skinWeights": [],
            "faces": [],
            "bones": [],
            "name": "praejimasGeometry",
            "vertices": [],
            "uvs": []
        },
        "type": "Geometry"
    },{
        "materials": [{
            "specularCoef": 50,
            "blending": "NormalBlending",
            "transparent": false,
            "colorEmissive": [0,0,0],
            "colorAmbient": [1,1,1],
            "shading": "phong",
            "mapSpecularWrap": ["RepeatWrapping","RepeatWrapping"],
            "depthWrite": true,
            "depthTest": true,
            "mapSpecularAnisotropy": 1,
            "mapDiffuseRepeat": [1,1],
            "opacity": 1,
            "mapDiffuse": "WoodDark_COLOR.png",
            "DbgColor": 15658734,
            "mapSpecularRepeat": [1,1],
            "mapDiffuseWrap": ["RepeatWrapping","RepeatWrapping"],
            "doubleSided": true,
            "mapDiffuseAnisotropy": 1,
            "colorSpecular": [0.004706,0.004706,0.004314],
            "DbgIndex": 0,
            "colorDiffuse": [1,1,1],
            "DbgName": "Wood_Dark_Polished",
            "mapSpecular": "WoodDark_SPEC.png",
            "visible": true,
            "wireframe": false
        }],
        "uuid": "E710EDC8-9506-3344-8848-32D4F0F13C91",
        "data": {
            "metadata": {
                "faces": 6,
                "generator": "io_three",
                "materials": 1,
                "bones": 0,
                "morphTargets": 0,
                "version": 3,
                "vertices": 8,
                "normals": 8,
                "uvs": 1
            },
            "skinIndices": [],
            "influencesPerVertex": 2,
            "morphTargets": [],
            "animations": [],
            "normals": [0.577349,-0.577349,0.577349,0.577349,-0.577349,-0.577349,0.577349,0.577349,-0.577349,0.577349,0.577349,0.577349,-0.577349,0.577349,0.577349,-0.577349,0.577349,-0.577349,-0.577349,-0.577349,-0.577349,-0.577349,-0.577349,0.577349],
            "skinWeights": [],
            "faces": [43,0,2,3,1,0,0,1,2,3,0,1,2,3,43,4,6,7,5,0,0,1,2,3,4,5,6,7,43,0,1,4,5,0,2,3,0,1,0,3,4,7,43,7,6,3,2,0,0,1,2,3,6,5,2,1,43,2,0,5,7,0,2,3,0,1,1,0,7,6,43,1,3,6,4,0,0,1,2,3,3,2,5,4],
            "bones": [],
            "name": "Box0Geometry",
            "vertices": [6.5,-2.75,0.075,6.5,2.75,0.075,6.5,-2.75,-0.075,6.5,2.75,-0.075,-6.5,2.75,0.075,-6.5,-2.75,0.075,-6.5,2.75,-0.075,-6.5,-2.75,-0.075],
            "uvs": [[0,1,0,0,1,0,1,1]]
        },
        "type": "Geometry"
    },{
        "materials": [{
            "specularCoef": 50,
            "blending": "NormalBlending",
            "transparent": false,
            "DbgIndex": 0,
            "colorEmissive": [0,0,0],
            "colorAmbient": [0.498039,0.498039,0.498039],
            "shading": "phong",
            "depthWrite": true,
            "depthTest": true,
            "colorDiffuse": [0.498039,0.498039,0.498039],
            "colorSpecular": [0.5,0.5,0.5],
            "DbgName": "Brown_Ground_Stones",
            "opacity": 1,
            "doubleSided": true,
            "DbgColor": 15658734,
            "visible": true,
            "wireframe": false
        }],
        "uuid": "4B173183-94A8-315E-A324-88490FEC0B0C",
        "data": {
            "metadata": {
                "faces": 6,
                "generator": "io_three",
                "materials": 1,
                "bones": 0,
                "morphTargets": 0,
                "version": 3,
                "vertices": 8,
                "normals": 8,
                "uvs": 1
            },
            "skinIndices": [],
            "influencesPerVertex": 2,
            "morphTargets": [],
            "animations": [],
            "normals": [0.577349,-0.577349,0.577349,0.577349,-0.577349,-0.577349,0.577349,0.577349,-0.577349,0.577349,0.577349,0.577349,-0.577349,0.577349,0.577349,-0.577349,0.577349,-0.577349,-0.577349,-0.577349,-0.577349,-0.577349,-0.577349,0.577349],
            "skinWeights": [],
            "faces": [43,0,2,3,1,0,0,1,2,3,0,1,2,3,43,4,6,7,5,0,0,1,2,3,4,5,6,7,43,0,1,4,5,0,2,3,0,1,0,3,4,7,43,7,6,3,2,0,0,1,2,3,6,5,2,1,43,2,0,5,7,0,2,3,0,1,1,0,7,6,43,1,3,6,4,0,0,1,2,3,3,2,5,4],
            "bones": [],
            "name": "grindysGeometry",
            "vertices": [30,-20,0.125,30,20,0.125,30,-20,-0.125,30,20,-0.125,-30,20,0.125,-30,-20,0.125,-30,20,-0.125,-30,-20,-0.125],
            "uvs": [[0,1,0,0,1,0,1,1]]
        },
        "type": "Geometry"
    },{
        "materials": [{
            "specularCoef": 50,
            "blending": "NormalBlending",
            "transparent": false,
            "colorEmissive": [0,0,0],
            "colorAmbient": [1,1,1],
            "shading": "phong",
            "mapSpecularWrap": ["RepeatWrapping","RepeatWrapping"],
            "depthWrite": true,
            "depthTest": true,
            "mapSpecularAnisotropy": 1,
            "mapDiffuseRepeat": [1,1],
            "opacity": 1,
            "mapDiffuse": "WoodDark_COLOR.png",
            "DbgColor": 15658734,
            "mapSpecularRepeat": [1,1],
            "mapDiffuseWrap": ["RepeatWrapping","RepeatWrapping"],
            "doubleSided": true,
            "mapDiffuseAnisotropy": 1,
            "colorSpecular": [0.004706,0.004706,0.004314],
            "DbgIndex": 0,
            "colorDiffuse": [1,1,1],
            "DbgName": "Wood_Dark_Polished",
            "mapSpecular": "WoodDark_SPEC.png",
            "visible": true,
            "wireframe": false
        }],
        "uuid": "0813763B-3A95-3717-A405-7EEF112B324A",
        "data": {
            "metadata": {
                "faces": 6,
                "generator": "io_three",
                "materials": 1,
                "bones": 0,
                "morphTargets": 0,
                "version": 3,
                "vertices": 8,
                "normals": 8,
                "uvs": 1
            },
            "skinIndices": [],
            "influencesPerVertex": 2,
            "morphTargets": [],
            "animations": [],
            "normals": [0.577349,-0.577349,0.577349,0.577349,-0.577349,-0.577349,0.577349,0.577349,-0.577349,0.577349,0.577349,0.577349,-0.577349,0.577349,0.577349,-0.577349,0.577349,-0.577349,-0.577349,-0.577349,-0.577349,-0.577349,-0.577349,0.577349],
            "skinWeights": [],
            "faces": [43,0,2,3,1,0,0,1,2,3,0,1,2,3,43,4,6,7,5,0,0,1,2,3,4,5,6,7,43,0,1,4,5,0,2,3,0,1,0,3,4,7,43,7,6,3,2,0,0,1,2,3,6,5,2,1,43,2,0,5,7,0,2,3,0,1,1,0,7,6,43,1,3,6,4,0,0,1,2,3,3,2,5,4],
            "bones": [],
            "name": "Box1Geometry",
            "vertices": [11.5,-2.75,0.125,11.5,2.75,0.125,11.5,-2.75,-0.125,11.5,2.75,-0.125,-11.5,2.75,0.125,-11.5,-2.75,0.125,-11.5,2.75,-0.125,-11.5,-2.75,-0.125],
            "uvs": [[0,1,0,0,1,0,1,1]]
        },
        "type": "Geometry"
    },{
        "materials": [],
        "uuid": "C3006688-4625-3AA6-B002-4324EBAFC957",
        "data": {
            "metadata": {
                "generator": "io_three",
                "materials": 0,
                "bones": 0,
                "morphTargets": 0,
                "version": 3,
                "vertices": 0,
                "normals": 0,
                "uvs": 0
            },
            "skinIndices": [],
            "influencesPerVertex": 2,
            "morphTargets": [],
            "animations": [],
            "normals": [],
            "skinWeights": [],
            "faces": [],
            "bones": [],
            "name": "sienosGeometry",
            "vertices": [],
            "uvs": []
        },
        "type": "Geometry"
    }],
    "metadata": {
        "type": "Object",
        "version": 4.4,
        "generator": "io_three"
    },
    "textures": [{
        "minFilter": 1008,
        "image": "0C31186D-399D-3638-911B-08BB97A9DF2E",
        "anisotropy": 1,
        "mapping": 300,
        "uuid": "84A9F74A-95A8-3BA3-84E1-D33D97E48E6D",
        "repeat": [1,1],
        "name": "WoodDark_COLOR_png",
        "magFilter": 1006,
        "wrap": [1000,1000]
    },{
        "minFilter": 1008,
        "image": "BD9F15AB-6708-340C-A18A-A6C73C312780",
        "anisotropy": 1,
        "mapping": 300,
        "uuid": "01794AFF-A466-362F-B795-41DADB6DBB8F",
        "repeat": [1,1],
        "name": "WoodDark_SPEC_png",
        "magFilter": 1006,
        "wrap": [1000,1000]
    }],
    "materials": [{
        "blending": "NormalBlending",
        "specular": 8355711,
        "color": 8355711,
        "uuid": "99C4E85C-4692-37C4-871B-9AF572C6E0AD",
        "depthWrite": true,
        "depthTest": true,
        "type": "MeshPhongMaterial",
        "shininess": 50,
        "side": 2,
        "name": "Brown_Ground_Stones",
        "vertexColors": false,
        "emissive": 0,
        "ambient": 8355711
    },{
        "blending": "NormalBlending",
        "specular": 197379,
        "color": 16711680,
        "uuid": "EBEEF0BF-3581-3563-AE10-379FF032D230",
        "depthWrite": true,
        "depthTest": true,
        "type": "MeshPhongMaterial",
        "shininess": 50,
        "side": 2,
        "name": "Physical1",
        "vertexColors": false,
        "emissive": 0,
        "ambient": 16711680
    },{
        "blending": "NormalBlending",
        "specular": 197379,
        "color": 16711680,
        "uuid": "42652D1D-8F39-3212-8099-23FA5765848D",
        "depthWrite": true,
        "depthTest": true,
        "type": "MeshPhongMaterial",
        "shininess": 50,
        "side": 2,
        "name": "Physical2",
        "vertexColors": false,
        "emissive": 0,
        "ambient": 16711680
    },{
        "blending": "NormalBlending",
        "specular": 8355711,
        "color": 8355711,
        "uuid": "F8223B4E-5A4D-3B9B-AFCA-9DEB6E7583F8",
        "depthWrite": true,
        "depthTest": true,
        "type": "MeshPhongMaterial",
        "shininess": 50,
        "side": 2,
        "name": "Red_Dark_Bricks",
        "vertexColors": false,
        "emissive": 0,
        "ambient": 8355711
    },{
        "blending": "NormalBlending",
        "specular": 8355711,
        "color": 11579568,
        "uuid": "B1A25C76-4115-3BE2-9603-A276405FB0AC",
        "depthWrite": true,
        "depthTest": true,
        "type": "MeshPhongMaterial",
        "shininess": 50,
        "side": 2,
        "name": "sienosDefault",
        "vertexColors": false,
        "emissive": 0,
        "ambient": 11579568
    },{
        "blending": "NormalBlending",
        "specular": 65793,
        "color": 16777215,
        "uuid": "0EF10C72-0E6F-3DB3-82EF-7FAFBD4447D2",
        "map": "84A9F74A-95A8-3BA3-84E1-D33D97E48E6D",
        "depthWrite": true,
        "depthTest": true,
        "type": "MeshPhongMaterial",
        "shininess": 50,
        "side": 2,
        "name": "Wood_Dark_Polished",
        "specularMap": "01794AFF-A466-362F-B795-41DADB6DBB8F",
        "vertexColors": false,
        "emissive": 0,
        "ambient": 16777215
    }],
    "images": [{
        "name": "WoodDark_COLOR.png",
        "url": "WoodDark_COLOR.png",
        "uuid": "0C31186D-399D-3638-911B-08BB97A9DF2E"
    },{
        "name": "WoodDark_SPEC.png",
        "url": "WoodDark_SPEC.png",
        "uuid": "BD9F15AB-6708-340C-A18A-A6C73C312780"
    }],
    "animations": [{
        "name": "default",
        "fps": 29,
        "tracks": [{
            "name": "CameraPreset.position",
            "keys": [{
                "time": 0,
                "value": [11.8289,14.8471,13.3672]
            },{
                "time": 120,
                "value": [11.8289,14.8471,13.3672]
            },{
                "time": 240,
                "value": [11.8289,14.8471,13.3672]
            },{
                "time": 360,
                "value": [11.8289,14.8471,13.3672]
            }],
            "type": "vector3"
        },{
            "name": "CameraPreset.scale",
            "keys": [{
                "time": 0,
                "value": [1,1,1]
            },{
                "time": 120,
                "value": [1,1,1]
            },{
                "time": 240,
                "value": [1,1,1]
            },{
                "time": 360,
                "value": [1,1,1]
            }],
            "type": "vector3"
        },{
            "name": "CameraPreset.quaternion",
            "keys": [{
                "time": 0,
                "value": [0,0.707107,0.707107,0]
            },{
                "time": 120,
                "value": [-0.612372,-0.353553,-0.353553,0.612372]
            },{
                "time": 240,
                "value": [-0.612372,0.353553,0.353553,0.612372]
            },{
                "time": 360,
                "value": [-0,0.707107,0.707107,0]
            }],
            "type": "quaternion"
        }]
    }],
    "object": {
        "type": "Scene",
        "uuid": "2D3D6F64-30D9-4F27-9EDD-F62853063628",
        "children": [{
            "name": "CameraPreset",
            "uuid": "B0C4E574-DECC-3D97-99F0-60577F3026BF",
            "matrix": [-1,0,-0,0,-0,0,1,0,0,1,0,0,11.8289,14.8471,13.3672,1],
            "visible": true,
            "type": "Object",
            "children": [{
                "name": "TurnTableCamera",
                "uuid": "D7C44AB9-C5E4-3E53-805E-02A6D8DC90EC",
                "matrix": [-0.94914,-0.314857,-0,0,0.040225,-0.121261,0.991805,0,-0.312277,0.941361,0.127759,0,5.9022,6.601,-0.5249,1],
                "visible": true,
                "type": "PerspectiveCamera",
                "far": 50000,
                "near": 0.1,
                "aspect": 1.77778,
                "fov": 27.7128
            }]
        },{
            "name": "grindys",
            "uuid": "41B053C4-C820-395B-AADE-F094D04059FE",
            "matrix": [-1,0,0,0,0,0,1,0,0,1,0,0,14.5349,0.2314,16.3293,1],
            "visible": false,
            "type": "Mesh",
            "material": "99C4E85C-4692-37C4-871B-9AF572C6E0AD",
            "castShadow": true,
            "receiveShadow": true,
            "geometry": "4B173183-94A8-315E-A324-88490FEC0B0C"
        },{
            "name": "Spinta",
            "uuid": "529A5E68-2848-369A-A264-16E6E9790F3E",
            "matrix": [-1,0,0,0,0,0,1,0,0,1,0,0,-1.9202,10.0396,0,1],
            "visible": true,
            "type": "Object",
            "children": [{
                "name": "Box",
                "uuid": "DDA9AE26-14F9-3E6A-9BDD-AF02F6D2F286",
                "matrix": [1,0,0,0,0,1,0,0,0,0,1,0,0.4421,0,-0.6929,1],
                "visible": true,
                "type": "Mesh",
                "material": "0EF10C72-0E6F-3DB3-82EF-7FAFBD4447D2",
                "castShadow": true,
                "receiveShadow": true,
                "geometry": "15641190-4052-3871-BF5E-F046F6B1B496"
            },{
                "name": "Box0",
                "uuid": "875292D1-FD43-3D0F-B1AC-1075C033A8EA",
                "matrix": [1,0,0,0,0,1,0,0,0,0,1,0,-4.3402,0,-8.6929,1],
                "visible": true,
                "type": "Mesh",
                "material": "0EF10C72-0E6F-3DB3-82EF-7FAFBD4447D2",
                "castShadow": true,
                "receiveShadow": true,
                "geometry": "E710EDC8-9506-3344-8848-32D4F0F13C91"
            },{
                "name": "Box1",
                "uuid": "13AB8362-B9AF-310A-8509-00DC96972EBC",
                "matrix": [1,0,0,0,0,1,0,0,0,0,1,0,0.4421,0,7.3071,1],
                "visible": true,
                "type": "Mesh",
                "material": "0EF10C72-0E6F-3DB3-82EF-7FAFBD4447D2",
                "castShadow": true,
                "receiveShadow": true,
                "geometry": "0813763B-3A95-3717-A405-7EEF112B324A"
            },{
                "name": "Box10",
                "uuid": "C80DC305-4B7A-395C-897F-E4767BA2D8A6",
                "matrix": [1,0,0,0,0,1,0,0,0,0,1,0,-4.3402,0,-4.6929,1],
                "visible": true,
                "type": "Mesh",
                "material": "0EF10C72-0E6F-3DB3-82EF-7FAFBD4447D2",
                "castShadow": true,
                "receiveShadow": true,
                "geometry": "5B23DCE7-72A6-31B5-B561-B5098FF6433E"
            },{
                "name": "Box2",
                "uuid": "66A008AC-44C6-3B23-9275-5237B57058C0",
                "matrix": [1,0,0,0,0,1,0,0,0,0,1,0,0.4421,0,3.3071,1],
                "visible": true,
                "type": "Mesh",
                "material": "EBEEF0BF-3581-3563-AE10-379FF032D230",
                "castShadow": true,
                "receiveShadow": true,
                "geometry": "A3266DF7-EF8B-3835-B919-F2D9B9D10D07"
            },{
                "name": "Null",
                "uuid": "8C60597C-A5D8-30C5-803B-493A7F445A92",
                "matrix": [1,0,0,0,0,1,0,0,0,0,1,0,10.0834,0,-9.76706,1],
                "visible": true,
                "type": "Object",
                "children": [{
                    "name": "Box3",
                    "uuid": "BF7F5BAE-ECAB-32A6-B7E6-0F0B02A66F3D",
                    "matrix": [-4e-06,0,27.5,0,0,5.5,0,0,-0.25,0,-0,0,0,0,13.7454,1],
                    "visible": true,
                    "type": "Mesh",
                    "material": "0EF10C72-0E6F-3DB3-82EF-7FAFBD4447D2",
                    "castShadow": true,
                    "receiveShadow": true,
                    "geometry": "DAF26EED-E8A1-3597-94D1-E65246622C91"
                },{
                    "name": "Box4",
                    "uuid": "21E1EE28-720A-3F5F-A701-169B87D161B6",
                    "matrix": [-3e-06,0,23.5,0,0,5.5,0,0,-0.25,0,-0,0,-12,0,11.7523,1],
                    "visible": true,
                    "type": "Mesh",
                    "material": "0EF10C72-0E6F-3DB3-82EF-7FAFBD4447D2",
                    "castShadow": true,
                    "receiveShadow": true,
                    "geometry": "21064AED-2F9E-349A-8048-33069A9BEACE"
                },{
                    "name": "Box5",
                    "uuid": "B7F31A6C-E829-3060-8AE1-EBA084A2865B",
                    "matrix": [-3e-06,0,25.5,0,0,5.5,0,0,-0.25,0,-0,0,-8,0,12.7427,1],
                    "visible": true,
                    "type": "Mesh",
                    "material": "0EF10C72-0E6F-3DB3-82EF-7FAFBD4447D2",
                    "castShadow": true,
                    "receiveShadow": true,
                    "geometry": "64183BD0-6EAE-3D88-8ABC-1117C3AD9D35"
                },{
                    "name": "Box6",
                    "uuid": "635989B7-6F0F-336A-8B27-DC1722994B13",
                    "matrix": [-3e-06,0,21.5,0,0,5.5,0,0,-0.25,0,-0,0,-16,0,10.7435,1],
                    "visible": true,
                    "type": "Mesh",
                    "material": "0EF10C72-0E6F-3DB3-82EF-7FAFBD4447D2",
                    "castShadow": true,
                    "receiveShadow": true,
                    "geometry": "5F05442A-9704-3BFB-BE1B-EE12E2150EE3"
                },{
                    "name": "Box7",
                    "uuid": "438FF972-AF36-3959-A474-DA6FFA57510C",
                    "matrix": [-3e-06,0,19.5,0,0,5.5,0,0,-0.25,0,-0,0,-20,0,9.746,1],
                    "visible": true,
                    "type": "Mesh",
                    "material": "0EF10C72-0E6F-3DB3-82EF-7FAFBD4447D2",
                    "castShadow": true,
                    "receiveShadow": true,
                    "geometry": "778708C3-2A4C-30ED-AC23-F99783DFA888"
                },{
                    "name": "Box9",
                    "uuid": "82475668-0D68-35E4-A7AD-6FC2EA1CDC6D",
                    "matrix": [-1e-06,0,8,0,0,5.5,0,0,-0.15,0,-0,0,-4.1458,0,13.1038,1],
                    "visible": true,
                    "type": "Mesh",
                    "material": "42652D1D-8F39-3212-8099-23FA5765848D",
                    "castShadow": true,
                    "receiveShadow": true,
                    "geometry": "98CE0ABF-982E-3010-BF1D-01919C9CB4EF"
                }]
            }]
        },{
            "name": "Spinta1",
            "uuid": "DC8795ED-75BD-38CA-8F83-1F82530B6B16",
            "matrix": [-1,0,0,0,0,0,1,0,0,1,0,0,-1.9202,10.0396,0,1],
            "visible": true,
            "type": "Object"
        },{
            "name": "SpotLight",
            "uuid": "1B18A08F-0404-3C2E-888D-7391D0AB1E6E",
            "matrix": [0.00329,0.050688,-0.998709,0,-0.282498,-0.957987,-0.049552,0,-0.959262,0.282296,0.011167,0,-32.6547,25.6262,22.3704,1],
            "visible": true,
            "type": "SpotLight",
            "castShadow": true,
            "color": 16777215,
            "intensity": 2,
            "distance": 0,
            "angle": 2.79253,
            "decayExponent": 2
        },{
            "name": "SpotLight1",
            "uuid": "D3F76104-364D-3D91-80D7-FB01739E4BBE",
            "matrix": [-1,0,0,0,0,0.078149,0.996942,0,0,0.996942,-0.078149,0,6.6504,23.7068,12.3775,1],
            "visible": true,
            "type": "SpotLight",
            "castShadow": true,
            "color": 16777215,
            "intensity": 0.5,
            "distance": 0,
            "angle": 2.0944,
            "decayExponent": 2
        }],
        "matrix": [1,0,0,0,0,1,0,0,0,0,1,0,0,0,0,1]
    }
}